xiao_try_publish_a_package/__init__.py
xiao_try_publish_a_package/main.py
LfMosh-0.0.1.dist-info/METADATA
LfMosh-0.0.1.dist-info/WHEEL
LfMosh-0.0.1.dist-info/top_level.txt
LfMosh-0.0.1.dist-info/RECORD
