Metadata-Version: 2.1
Name: LfMosh
Version: 0.0.1
Summary: Learning from Mosh
License: UNKNOWN
Platform: UNKNOWN
